fastash-0.0.19.dist-info/LICENSE
fastash-0.0.19.dist-info/top_level.txt
fastash-0.0.19.dist-info/WHEEL
fastash-0.0.19.dist-info/METADATA
fastash-0.0.19.dist-info/RECORD
fastash/__init__.py
fastash/hyperplane.py
fastash/whitening_transformer.py
fastash/ash.py
fastash/ashfunc.cpython-38-x86_64-linux-gnu.so
fastash/datasets.py
fastash/bandwidth_selection/__init__.py
fastash/bandwidth_selection/_scotts_rule.py
