Metadata-Version: 2.1
Name: fastash
Version: 0.0.19
Summary: Fast Averaged Shifted Histogram module.
Home-page: https://gitlab.inria.fr/fmazy/fastash
Author: François-Rémi Mazy
Author-email: francois-remi.mazy@inria.fr
License: BSD 3-Clause License
Platform: UNKNOWN
Requires-Dist: numpy (>=1.19.2)
